iplocate/__init__.py
iplocate/iplocate.py
iplocator-1.0.1.dist-info/LICENSE
iplocator-1.0.1.dist-info/METADATA
iplocator-1.0.1.dist-info/WHEEL
iplocator-1.0.1.dist-info/entry_points.txt
iplocator-1.0.1.dist-info/top_level.txt
iplocator-1.0.1.dist-info/RECORD
