Metadata-Version: 2.1
Name: iplocator
Version: 1.0.1
Summary: The ultimate tool for IP location within the CLI, especially made for Hackers
Home-page: https://github.com/sayanbiswas9/iplocate
Author: Sayan Biswas
Author-email: anonys0101@duck.com
Classifier: Programming Language :: Python :: 3
Classifier: License :: OSI Approved :: MIT License
Classifier: Operating System :: OS Independent
Requires-Python: >=2.0
License-File: LICENSE
Requires-Dist: requests
